pyacvd/clustering.py
pyacvd/__init__.py
pyacvd/_clustering.cpython-310-darwin.so
pyacvd/_clustering.pyi
pyacvd-0.3.2.dist-info/RECORD
pyacvd-0.3.2.dist-info/WHEEL
pyacvd-0.3.2.dist-info/METADATA
pyacvd-0.3.2.dist-info/licenses/LICENSE
