Metadata-Version: 2.1
Name: pyacvd
Version: 0.3.2
Summary: Uniformly remeshes surface meshes
Keywords: vtk,uniform,meshing,remeshing,acvd
Author-Email: Alex Kaszynski <akascap@gmail.com>
Classifier: License :: OSI Approved :: MIT License
Classifier: Operating System :: Microsoft :: Windows
Classifier: Operating System :: POSIX
Classifier: Intended Audience :: Science/Research
Classifier: Programming Language :: Python :: 3.9
Classifier: Programming Language :: Python :: 3.10
Classifier: Programming Language :: Python :: 3.11
Classifier: Programming Language :: Python :: 3.12
Classifier: Programming Language :: Python :: 3.13
Requires-Python: >=3.9
Requires-Dist: numpy
Requires-Dist: pyvista>=0.37.0
Requires-Dist: pykdtree
Provides-Extra: test
Requires-Dist: pytest; extra == "test"
